cgen2gmx.py
src/classes.py
src/config.py
src/get_uniques.py
src/parse_files.py
cgen2gmx-1.1.0.dist-info/LICENSE
cgen2gmx-1.1.0.dist-info/METADATA
cgen2gmx-1.1.0.dist-info/WHEEL
cgen2gmx-1.1.0.dist-info/entry_points.txt
cgen2gmx-1.1.0.dist-info/top_level.txt
cgen2gmx-1.1.0.dist-info/RECORD
