Metadata-Version: 2.1
Name: cgen2gmx
Version: 1.1.0
Summary: A small commandline tool for managing forcefield parameters used in molecular dynamics simulations
Home-page: https://github.com/chrispy67/cgen2gmx
Author: Christian Phillips 
Author-email: christian_phillips1@msn.com
Project-URL: Bug Reports, https://github.com/chrispy67/cgen2gmx/issues
Project-URL: Source, https://github.com/chrispy67/cgen2gmx
Keywords: molecular dynamics,charmm,forcefield,computational chemistry
Classifier: Development Status :: 1 - Planning
Classifier: License :: OSI Approved :: MIT License
Classifier: Programming Language :: Python :: 3
Requires-Python: >=3.7
License-File: LICENSE
